Workbook

Sheet Summary
A1: Paul Asset Allocation Optimization Model
A3: Purpose | B3: Optimize five risk-level portfolios using compound return, volatility, and correlation assumptions with visible constraints.
A4: Methods | B4: Main allocation is the target-volatility MVO result. Monte Carlo simulation is currently removed from all calculations.
A5: Important | B5: This is a planning model, not investment advice. Correlations and constraints are starter assumptions that should be reviewed.
A7: Model Status | B7: =IF(Checks!G2="OK","OK","Review checks")
A9: Main Recommended Allocation: MVO
A10: Portfolio | B10: Expected Return | C10: Volatility | D10: Sharpe vs Cash | E10: Equity | F10: Fixed Income | G10: Alternatives | H10: Cash | I10: Target Vol Min | J10: Target Vol Max | K10: Target Status
A11: Conservative | B11: 0.05756 | C11: 0.083325 | D11: 0.318757 | E11: 0.302111 | F11: 0.687889 | G11: 0 | H11: 0.01 | I11: 0.07332473 | J11: 0.08332473 | K11: In target
A12: Balanced | B12: 0.06447 | C12: 0.115447 | D12: 0.289915 | E12: 0.55 | F12: 0.44 | G12: 0 | H12: 0.01 | I12: 0.1054472 | J12: 0.1154472 | K12: In target
A13: Moderate | B13: 0.066319 | C13: 0.129065 | D13: 0.27365 | E13: 0.65 | F13: 0.34 | G13: 0 | H13: 0.01 | I13: 0.12306511 | J13: 0.12906511 | K13: In target
A14: Growth | B14: 0.068586 | C14: 0.147783 | D14: 0.254334 | E14: 0.817936 | F14: 0.172064 | G14: 0 | H14: 0.01 | I14: 0.13778322 | J14: 0.14778322 | K14: In target
A15: Aggressive Growth | B15: 0.07064 | C15: 0.167147 | D15: 0.237157 | E15: 0.99 | F15: 0 | G15: 0 | H15: 0.01 | I15: 0.15768767 | J15: 0.16768767 | K15: In target
A18: Target Volatility Optimized Overall Allocation
A19: Portfolio | B19: Expected Return | C19: Volatility | D19: Sharpe vs Cash | E19: Equity | F19: Fixed Income | G19: Alternatives | H19: Cash | I19: Target Vol Min | J19: Target Vol Max | K19: Target Status
A20: Conservative | B20: 0.05756 | C20: 0.083325 | D20: 0.318757 | E20: 0.302111 | F20: 0.687889 | G20: 0 | H20: 0.01 | I20: 0.07332473 | J20: 0.08332473 | K20: In target
A21: Balanced | B21: 0.06447 | C21: 0.115447 | D21: 0.289915 | E21: 0.55 | F21: 0.44 | G21: 0 | H21: 0.01 | I21: 0.1054472 | J21: 0.1154472 | K21: In target
A22: Moderate | B22: 0.066319 | C22: 0.129065 | D22: 0.27365 | E22: 0.65 | F22: 0.34 | G22: 0 | H22: 0.01 | I22: 0.12306511 | J22: 0.12906511 | K22: In target
A23: Growth | B23: 0.068586 | C23: 0.147783 | D23: 0.254334 | E23: 0.817936 | F23: 0.172064 | G23: 0 | H23: 0.01 | I23: 0.13778322 | J23: 0.14778322 | K23: In target
A24: Aggressive Growth | B24: 0.07064 | C24: 0.167147 | D24: 0.237157 | E24: 0.99 | F24: 0 | G24: 0 | H24: 0.01 | I24: 0.15768767 | J24: 0.16768767 | K24: In target

Sheet Asset Inputs
A1: Asset | B1: Category | C1: Source Name(s) | D1: Compound Return | E1: Volatility | F1: Min Weight | G1: Max Weight | H1: Source Mapping
A2: U.S. Large Cap | B2: Equity | C2: U.S. Large Cap | D2: 0.067 | E2: 0.16470142 | F2: 0.2 | G2: 0.45 | H2: U.S. Large Cap
A3: U.S. Mid Cap | B3: Equity | C3: U.S. Mid Cap | D3: 0.07 | E3: 0.18562979 | F3: 0 | G3: 0.2 | H3: U.S. Mid Cap
A4: U.S. Small Cap | B4: Equity | C4: U.S. Small Cap | D4: 0.069 | E4: 0.21097071 | F4: 0 | G4: 0.05 | H4: U.S. Small Cap
A5: International Developed Equity | B5: Equity | C5: EAFE Equity | D5: 0.081 | E5: 0.17629457 | F5: 0.1 | G5: 0.2 | H5: EAFE Equity
A6: Emerging Markets Equity | B6: Equity | C6: Emerging Markets Equity | D6: 0.072 | E6: 0.20933183 | F6: 0 | G6: 0.1 | H6: Emerging Markets Equity
A7: U.S. REITs | B7: Alternatives | C7: U.S. REITs | D7: 0.08 | E7: 0.17396879 | F7: 0 | G7: 0 | H7: U.S. REITs
A8: Commodities | B8: Alternatives | C8: Commodities | D8: 0.038 | E8: 0.18318431 | F8: 0 | G8: 0 | H8: Commodities
A9: Income U.S. - U.S. Treasury | B9: Fixed Income | C9: U.S. Intermediate Treasuries, U.S. Long Treasuries, TIPS | D9: 0.040666667 | E9: 0.067602385 | F9: 0 | G9: 0.45 | H9: Equal-weight U.S. Intermediate Treasuries, U.S. Long Treasuries, and TIPS
A10: Income U.S. Government Related | B10: Fixed Income | C10: U.S. Aggregate Bonds, U.S. Muni 1-15 Yr Blend | D10: 0.041 | E10: 0.041558053 | F10: 0 | G10: 0.35 | H10: Equal-weight U.S. Aggregate Bonds and U.S. Muni 1-15 Yr Blend
A11: Income U.S. Corporate | B11: Fixed Income | C11: U.S. Inv Grade Corporate Bonds, U.S. High Yield Bonds | D11: 0.0555 | E11: 0.073710021 | F11: 0 | G11: 0.4 | H11: Equal-weight U.S. Investment Grade Corporate Bonds and U.S. High Yield Bonds
A12: Income U.S. Securitized | B12: Fixed Income | C12: U.S. Securitized | D12: 0.049 | E12: 0.041859404 | F12: 0 | G12: 0.03 | H12: U.S. Securitized
A13: Fixed Income International | B13: Fixed Income | C13: World ex-U.S. Government Bonds hedged, Emerging Markets Sovereign Debt, Emerging Markets Corporate Bonds | D13: 0.052666667 | E13: 0.060209328 | F13: 0 | G13: 0.1 | H13: Equal-weight World ex-U.S. Government Bonds hedged, Emerging Markets Sovereign Debt, and Emerging Markets Corporate Bonds
... A15: Cash | B15: Cash | C15: U.S. Cash | D15: 0.031 | E15: 0.0066929904 | F15: 0.01 | G15: 0.01 | H15: U.S. Cash

Sheet MVO Detail
A1: Asset | B1: Category | C1: Conservative | D1: Balanced | E1: Moderate | F1: Growth | G1: Aggressive Growth
A2: U.S. Large Cap | B2: Equity | C2: 0.2 | D2: 0.239219 | E2: 0.2 | F2: 0.317936 | G2: 0.44
A3: U.S. Mid Cap | B3: Equity | C3: 0 | D3: 0.02115 | E3: 0.15 | F3: 0.2 | G3: 0.2
A4: U.S. Small Cap | B4: Equity | C4: 0 | D4: 0 | E4: 0 | F4: 0 | G4: 0.05
A5: International Developed Equity | B5: Equity | C5: 0.102111 | D5: 0.2 | E5: 0.2 | F5: 0.2 | G5: 0.2
A6: Emerging Markets Equity | B6: Equity | C6: 0 | D6: 0.089631 | E6: 0.1 | F6: 0.1 | G6: 0.1
A7: U.S. REITs | B7: Alternatives | C7: 0 | D7: 0 | E7: 0 | F7: 0 | G7: 0
A8: Commodities | B8: Alternatives | C8: 0 | D8: 0 | E8: 0 | F8: 0 | G8: 0
A9: Income U.S. - U.S. Treasury | B9: Fixed Income | C9: 0.002264 | D9: 0 | E9: 0 | F9: 0 | G9: 0
A10: Income U.S. Government Related | B10: Fixed Income | C10: 0.145625 | D10: 0 | E10: 0 | F10: 0 | G10: 0
A11: Income U.S. Corporate | B11: Fixed Income | C11: 0.4 | D11: 0.311147 | E11: 0.301335 | F11: 0.162064 | G11: 0
A12: Income U.S. Securitized | B12: Fixed Income | C12: 0.03 | D12: 0.03 | E12: 0.028665 | F12: 0 | G12: 0
A13: Fixed Income International | B13: Fixed Income | C13: 0.1 | D13: 0.088853 | E13: 0 | F13: 0 | G13: 0
... A15: Cash | B15: Cash | C15: 0.01 | D15: 0.01 | E15: 0.01 | F15: 0.01 | G15: 0.01
A16: Total | B16: Check | C16: =SUM(C2:C15) | D16: =SUM(D2:D15) | E16: =SUM(E2:E15) | F16: =SUM(F2:F15) | G16: =SUM(G2:G15)

Sheet Scenario Detail
A1: Bad Economy Optimized Overall Allocation
A2: Portfolio | B2: Expected Return | C2: Volatility | D2: Sharpe | E2: Equity | F2: Fixed Income | G2: Alternatives | H2: Cash | I2: Target Vol Min | J2: Target Vol Max | K2: Target Status
A3: Conservative | B3: 0.010611 | C3: 0.074644 | D3: -0.273156 | E3: 0.3 | F3: 0.69 | G3: 0 | H3: 0.01 | I3: 0.07332473 | J3: 0.08332473 | K3: In target
A4: Balanced | B4: 0.002659 | C4: 0.105447 | D4: -0.268766 | E4: 0.55 | F4: 0.44 | G4: 0 | H4: 0.01 | I4: 0.1054472 | J4: 0.1154472 | K4: In target
A5: Moderate | B5: -0.00108 | C5: 0.123065 | D5: -0.260676 | E5: 0.65 | F5: 0.34 | G5: 0 | H5: 0.01 | I5: 0.12306511 | J5: 0.12906511 | K5: In target
A6: Growth | B6: -0.00588 | C6: 0.137783 | D6: -0.26767 | E6: 0.750985 | F6: 0.239015 | G6: 0 | H6: 0.01 | I6: 0.13778322 | J6: 0.14778322 | K6: In target
A7: Aggressive Growth | B7: -0.013175 | C7: 0.157688 | D7: -0.28014 | E7: 0.90843 | F7: 0.08157 | G7: 0 | H7: 0.01 | I7: 0.15768767 | J7: 0.16768767 | K7: In target
A10: Median Economy Optimized Overall Allocation
A11: Portfolio | B11: Expected Return | C11: Volatility | D11: Sharpe | E11: Equity | F11: Fixed Income | G11: Alternatives | H11: Cash | I11: Target Vol Min | J11: Target Vol Max | K11: Target Status
A12: Conservative | B12: 0.05756 | C12: 0.083325 | D12: 0.318757 | E12: 0.302111 | F12: 0.687889 | G12: 0 | H12: 0.01 | I12: 0.07332473 | J12: 0.08332473 | K12: In target
A13: Balanced | B13: 0.06447 | C13: 0.115447 | D13: 0.289915 | E13: 0.55 | F13: 0.44 | G13: 0 | H13: 0.01 | I13: 0.1054472 | J13: 0.1154472 | K13: In target
A14: Moderate | B14: 0.066319 | C14: 0.129065 | D14: 0.27365 | E14: 0.65 | F14: 0.34 | G14: 0 | H14: 0.01 | I14: 0.12306511 | J14: 0.12906511 | K14: In target
A15: Growth | B15: 0.068586 | C15: 0.147783 | D15: 0.254334 | E15: 0.817936 | F15: 0.172064 | G15: 0 | H15: 0.01 | I15: 0.13778322 | J15: 0.14778322 | K15: In target
A16: Aggressive Growth | B16: 0.07064 | C16: 0.167147 | D16: 0.237157 | E16: 0.99 | F16: 0 | G16: 0 | H16: 0.01 | I16: 0.15768767 | J16: 0.16768767 | K16: In target
A19: Good Economy Optimized Overall Allocation
A20: Portfolio | B20: Expected Return | C20: Volatility | D20: Sharpe | E20: Equity | F20: Fixed Income | G20: Alternatives | H20: Cash | I20: Target Vol Min | J20: Target Vol Max | K20: Target Status
A21: Conservative | B21: 0.110039 | C21: 0.083325 | D21: 0.948571 | E21: 0.409057 | F21: 0.580943 | G21: 0 | H21: 0.01 | I21: 0.07332473 | J21: 0.08332473 | K21: In target
A22: Balanced | B22: 0.131815 | C22: 0.115447 | D22: 0.873257 | E22: 0.64 | F22: 0.35 | G22: 0 | H22: 0.01 | I22: 0.1054472 | J22: 0.1154472 | K22: In target
A23: Moderate | B23: 0.13959 | C23: 0.129065 | D23: 0.841361 | E23: 0.735525 | F23: 0.254475 | G23: 0 | H23: 0.01 | I23: 0.12306511 | J23: 0.12906511 | K23: In target
A24: Growth | B24: 0.149093 | C24: 0.147783 | D24: 0.799099 | E24: 0.85 | F24: 0.14 | G24: 0 | H24: 0.01 | I24: 0.13778322 | J24: 0.14778322 | K24: In target
A25: Aggressive Growth | B25: 0.158841 | C25: 0.167147 | D25: 0.764844 | E25: 0.99 | F25: 0 | G25: 0 | H25: 0.01 | I25: 0.15768767 | J25: 0.16768767 | K25: In target

Sheet Constraints
A1: Portfolio | B1: Category | C1: Minimum | D1: Maximum | E1: Target Vol Min | F1: Target Vol Max | G1: Notes
A2: Conservative | B2: Equity | C2: 0.3 | D2: 0.5 | E2: 0.07332473 | F2: 0.08332473 | G2: Editable policy band used by optimizer script
A3: Conservative | B3: Fixed Income | C3: 0.55 | D3: 0.75 | E3: 0.07332473 | F3: 0.08332473 | G3: Editable policy band used by optimizer script
A4: Conservative | B4: Alternatives | C4: 0 | D4: 0 | E4: 0.07332473 | F4: 0.08332473 | G4: Editable policy band used by optimizer script
A5: Conservative | B5: Cash | C5: 0.01 | D5: 0.01 | E5: 0.07332473 | F5: 0.08332473 | G5: Editable policy band used by optimizer script
A6: Balanced | B6: Equity | C6: 0.55 | D6: 0.65 | E6: 0.1054472 | F6: 0.1154472 | G6: Editable policy band used by optimizer script
A7: Balanced | B7: Fixed Income | C7: 0.35 | D7: 0.55 | E7: 0.1054472 | F7: 0.1154472 | G7: Editable policy band used by optimizer script
A8: Balanced | B8: Alternatives | C8: 0 | D8: 0 | E8: 0.1054472 | F8: 0.1154472 | G8: Editable policy band used by optimizer script
A9: Balanced | B9: Cash | C9: 0.01 | D9: 0.01 | E9: 0.1054472 | F9: 0.1154472 | G9: Editable policy band used by optimizer script
A10: Moderate | B10: Equity | C10: 0.65 | D10: 0.75 | E10: 0.12306511 | F10: 0.12906511 | G10: Editable policy band used by optimizer script
A11: Moderate | B11: Fixed Income | C11: 0.25 | D11: 0.4 | E11: 0.12306511 | F11: 0.12906511 | G11: Editable policy band used by optimizer script
A12: Moderate | B12: Alternatives | C12: 0 | D12: 0 | E12: 0.12306511 | F12: 0.12906511 | G12: Editable policy band used by optimizer script
A13: Moderate | B13: Cash | C13: 0.01 | D13: 0.01 | E13: 0.12306511 | F13: 0.12906511 | G13: Editable policy band used by optimizer script
... A21: Aggressive Growth | B21: Cash | C21: 0.01 | D21: 0.01 | E21: 0.15768767 | F21: 0.16768767 | G21: Editable policy band used by optimizer script
A23: Asset | B23: Sleeve Range Min | C23: Sleeve Range Max | D23: Notes
A24: U.S. Large Cap | B24: 0.2 | C24: 0.45 | D24: Direct asset-level bounds used by optimizer
A25: U.S. Mid Cap | B25: 0 | C25: 0.2 | D25: Direct asset-level bounds used by optimizer
A26: U.S. Small Cap | B26: 0 | C26: 0.05 | D26: Direct asset-level bounds used by optimizer
A27: International Developed Equity | B27: 0.1 | C27: 0.2 | D27: Direct asset-level bounds used by optimizer
A28: Emerging Markets Equity | B28: 0 | C28: 0.1 | D28: Direct asset-level bounds used by optimizer
A29: U.S. REITs | B29: 0 | C29: 0 | D29: Direct asset-level bounds used by optimizer
A30: Commodities | B30: 0 | C30: 0 | D30: Direct asset-level bounds used by optimizer
A31: Income U.S. - U.S. Treasury | B31: 0 | C31: 0.45 | D31: Direct asset-level bounds used by optimizer
A32: Income U.S. Government Related | B32: 0 | C32: 0.35 | D32: Direct asset-level bounds used by optimizer
A33: Income U.S. Corporate | B33: 0 | C33: 0.4 | D33: Direct asset-level bounds used by optimizer
A34: Income U.S. Securitized | B34: 0 | C34: 0.03 | D34: Direct asset-level bounds used by optimizer
A35: Fixed Income International | B35: 0 | C35: 0.1 | D35: Direct asset-level bounds used by optimizer
... A37: Cash | B37: 0.01 | C37: 0.01 | D37: Direct asset-level bounds used by optimizer

Sheet Checks
A1: Check | B1: Actual | C1: Expected | D1: Difference | E1: Tolerance | F1: Status | G1: Model Status
A2: Conservative MVO weights sum to 100% | B2: ='MVO Detail'!C17 | C2: 1 | D2: =B2-C2 | E2: 0.0001 | F2: =IF(ABS(D2)<=E2,"OK","Review") | G2: =IF(COUNTIF(F2:F2,"Review")=0,"OK","Review")
A3: Balanced MVO weights sum to 100% | B3: ='MVO Detail'!D17 | C3: 1 | D3: =B3-C3 | E3: 0.0001 | F3: =IF(ABS(D3)<=E3,"OK","Review") | G3: =IF(COUNTIF(F2:F3,"Review")=0,"OK","Review")
A4: Moderate MVO weights sum to 100% | B4: ='MVO Detail'!E17 | C4: 1 | D4: =B4-C4 | E4: 0.0001 | F4: =IF(ABS(D4)<=E4,"OK","Review") | G4: =IF(COUNTIF(F2:F4,"Review")=0,"OK","Review")
A5: Growth MVO weights sum to 100% | B5: ='MVO Detail'!F17 | C5: 1 | D5: =B5-C5 | E5: 0.0001 | F5: =IF(ABS(D5)<=E5,"OK","Review") | G5: =IF(COUNTIF(F2:F5,"Review")=0,"OK","Review")
A6: Aggressive Growth MVO weights sum to 100% | B6: ='MVO Detail'!G17 | C6: 1 | D6: =B6-C6 | E6: 0.0001 | F6: =IF(ABS(D6)<=E6,"OK","Review") | G6: =IF(COUNTIF(F2:F6,"Review")=0,"OK","Review")
A7: Conservative MVO cash equals 1% | B7: ='MVO Detail'!C15 | C7: 0.01 | D7: =B7-C7 | E7: 0.0001 | F7: =IF(ABS(D7)<=E7,"OK","Review")
A8: Balanced MVO cash equals 1% | B8: ='MVO Detail'!D15 | C8: 0.01 | D8: =B8-C8 | E8: 0.0001 | F8: =IF(ABS(D8)<=E8,"OK","Review")
A9: Moderate MVO cash equals 1% | B9: ='MVO Detail'!E15 | C9: 0.01 | D9: =B9-C9 | E9: 0.0001 | F9: =IF(ABS(D9)<=E9,"OK","Review")
A10: Growth MVO cash equals 1% | B10: ='MVO Detail'!F15 | C10: 0.01 | D10: =B10-C10 | E10: 0.0001 | F10: =IF(ABS(D10)<=E10,"OK","Review")
A11: Aggressive Growth MVO cash equals 1% | B11: ='MVO Detail'!G15 | C11: 0.01 | D11: =B11-C11 | E11: 0.0001 | F11: =IF(ABS(D11)<=E11,"OK","Review")
A12: All MVO sub-weights are non-negative | B12: =MIN('MVO Detail'!C2:G16) | C12: 0 | D12: =B12-C12 | E12: 0 | F12: =IF(B12>=0,"OK","Review")

Sheet Sources and Setup
A1: Item | B1: Current Treatment | C1: What to Decide Next
A2: Source file | B2: Matrix file read from C:\Users\hclevenger\Desktop\Paul Asset Allocation\inputs\matrix-usd.xlsx; compound return, annualized volatility, and correlations are used. | C2: Confirm source file version each quarter.
A3: PDF attachments | B3: Scan_260717_102740.pdf and Scan_260717_102947.pdf are present but no longer used in the optimizer. | C3: Keep or remove from source archive.
A4: Return source | B4: Compound return only. | C4: Confirm this remains the preferred expected return basis.
A5: Risk model | B5: Uses annualized volatility and correlation matrix from matrix-usd.xlsx. | C5: Review asset mappings for grouped fixed income sleeves.
A6: Monte Carlo | B6: Removed from all calculations for now. | C6: Redesign simulation methodology before adding it back.
A7: Five portfolios | B7: Category bands and target volatility ranges are explicit on Constraints tab; cash is hard-coded with both minimum and maximum at 1% in every model. | C7: Approve or revise the equity/fixed income/alternatives policy bands and target volatility bands.
A8: Tax/location | B8: Not modeled. | C8: Decide taxable vs qualified account treatment, muni bond role, and tax-aware placement.
A9: Liquidity/implementation | B9: No ETF/mutual fund tickers selected yet. | C9: Map each style sleeve to actual funds and expense ratios.
A10: Rebalancing | B10: Not modeled. | C10: Choose annual, semiannual, or tolerance-band rebalancing.
